persiann_api/__init__.py
persiann_api/download.py
persiann_api/main.py
persiann_api/select_bb.py
persiann_api/to_geotiff.py
persiann_api-0.1.1.dist-info/WHEEL
persiann_api-0.1.1.dist-info/METADATA
persiann_api-0.1.1.dist-info/RECORD
