Metadata-Version: 2.1
Name: persiann-api
Version: 0.1.1
Summary: Unofficial PERSIANN Python API.
Home-page: https://github.com/Martins6/persiann_api
License: Unlicense
Author: martins6
Author-email: adrielfalcao@gmail.com
Requires-Python: >=3.8,<3.11
Classifier: License :: Other/Proprietary License
Classifier: Programming Language :: Python :: 3
Classifier: Programming Language :: Python :: 3.10
Classifier: Programming Language :: Python :: 3.8
Classifier: Programming Language :: Python :: 3.9
Requires-Dist: GDAL (>=3.3.2)
Requires-Dist: Pillow (>=9.0.0,<10.0.0)
Requires-Dist: numpy (>=1.21.5,<2.0.0)
Requires-Dist: setuptools (==57.5.0)
Project-URL: Repository, https://github.com/Martins6/persiann_api
